{
	"static": {
		"style": {
			"position": "static"
		}
	},
	"fixed": {
		"style": {
			"position": "fixed"
		}
	},
	"absolute": {
		"style": {
			"position": "absolute"
		}
	},
	"relative": {
		"style": {
			"position": "relative"
		}
	},
	"block": {
		"style": {
			"display": "block"
		}
	},
	"inline": {
		"style": {
			"display": "inline"
		}
	},
	"flex": {
		"style": {
			"display": "flex"
		}
	},
	"hidden": {
		"style": {
			"display": "none"
		}
	},
	"h-64": {
		"style": {
			"height": 256
		}
	},
	"w-full": {
		"style": {
			"width": "100%"
		}
	},
	"border": {
		"style": {
			"borderTopWidth": 1,
			"borderRightWidth": 1,
			"borderBottomWidth": 1,
			"borderLeftWidth": 1
		}
	},
	"bg-white": {
		"style": {
			"--tw-bg-opacity": 1,
			"backgroundColor": "rgb(255 255 255 / var(--tw-bg-opacity))"
		}
	},
	"px-10": {
		"style": {
			"paddingLeft": 40,
			"paddingRight": 40
		}
	},
	"pb-0": {
		"style": {
			"paddingBottom": 0
		}
	},
	"pt-5": {
		"style": {
			"paddingTop": 20
		}
	},
	"text-sm": {
		"style": {
			"fontSize": 14,
			"lineHeight": 20
		}
	},
	"uppercase": {
		"style": {
			"textTransform": "uppercase"
		}
	},
	"capitalize": {
		"style": {
			"textTransform": "capitalize"
		}
	},
	"text-blue-700": {
		"style": {
			"--tw-text-opacity": 1,
			"color": "rgb(29 78 216 / var(--tw-text-opacity))"
		}
	}
}